vprad/__init__.py
vprad/actions/__init__.py
vprad/actions/apps.py
vprad/actions/decorators.py
vprad/actions/forms.py
vprad/actions/jinja.py
vprad/actions/jinja2/vprad/actions/action.jinja.html
vprad/actions/registry.py
vprad/actions/signals.py
vprad/actions/types.py
vprad/actions/urls.py
vprad/actions/views.py
vprad/auth/__init__.py
vprad/auth/jinja.py
vprad/auth/types.py
vprad/auth/urlsign.py
vprad/conf/__init__.py
vprad/conf/defaults.py
vprad/helpers.py
vprad/site/__init__.py
vprad/site/apps.py
vprad/site/jinja/__init__.py
vprad/site/jinja/decorators.py
vprad/site/jinja/globals.py
vprad/site/jinja2/vprad/base.jinja.html
vprad/site/jinja2/vprad/home.jinja.html
vprad/site/jinja2/vprad/layout/_base.jinja.html
vprad/site/jinja2/vprad/layout/_left_menu.jinja.html
vprad/site/jinja2/vprad/layout/_top_menu.jinja.html
vprad/site/jinja2/vprad/macros/actstream.html
vprad/site/jinja2/vprad/views/logout.jinja.html
vprad/site/urls.py
vprad/static/brand/favicon512x512.png
vprad/static/brand/logo_dark_bg.png
vprad/static/brand/logo_light_bg.png
vprad/static/vprad/vprad.css
vprad/static/vprad/vprad.js
vprad/templates_old/vprad/_base.html
vprad/templates_old/vprad/action.html
vprad/templates_old/vprad/base.html
vprad/templates_old/vprad/layouts/_left_menu.html
vprad/templates_old/vprad/layouts/_top_menu.html
vprad/templates_old/vprad/layouts/with_sidebar.html
vprad/templates_old/vprad/partials/actstream_star.html
vprad/templates_old/vprad/render_partials/field_value.html
vprad/templates_old/vprad/simple_detail.html
vprad/templates_old/vprad/templatetags/fields_as_list.html
vprad/templates_old/vprad/templatetags/fields_as_table.html
vprad/views/__init__.py
vprad/views/apps.py
vprad/views/defaults.py
vprad/views/generic/__init__.py
vprad/views/generic/detail.py
vprad/views/generic/embedding.py
vprad/views/generic/list.py
vprad/views/generic/mixin.py
vprad/views/helpers.py
vprad/views/jinja.py
vprad/views/jinja2/vprad/views/detail/embedded_object_detail.jinja.html
vprad-0.1.0.dist-info/LICENSE.txt
vprad-0.1.0.dist-info/WHEEL
vprad-0.1.0.dist-info/METADATA
vprad-0.1.0.dist-info/RECORD
